lifeguard_k8s/__init__.py
lifeguard_k8s/settings.py
lifeguard_k8s/actions/__init__.py
lifeguard_k8s/actions/pods.py
lifeguard_k8s/infrastructure/__init__.py
lifeguard_k8s/infrastructure/deployments.py
lifeguard_k8s/infrastructure/namespaces.py
lifeguard_k8s/infrastructure/pods.py
lifeguard_k8s/validations/__init__.py
lifeguard_k8s/validations/pods.py
tests/__init__.py
tests/actions/__init__.py
tests/actions/test_pods.py
tests/infrastructure/__init__.py
tests/infrastructure/test_deployments.py
tests/infrastructure/test_namespaces.py
tests/infrastructure/test_pods.py
tests/validations/__init__.py
tests/validations/test_pods.py
lifeguard_k8s-1.3.0.dist-info/METADATA
lifeguard_k8s-1.3.0.dist-info/WHEEL
lifeguard_k8s-1.3.0.dist-info/top_level.txt
lifeguard_k8s-1.3.0.dist-info/RECORD
