Metadata-Version: 2.1
Name: lifeguard-k8s
Version: 1.3.0
Summary: Lifeguard integration with Kubernetes
Home-page: https://github.com/LifeguardSystem/lifeguard-k8s
Author: Diego Rubin
Author-email: contact@diegorubin.dev
License: GPL2
Classifier: Development Status :: 4 - Beta
Classifier: Environment :: Plugins
Classifier: Intended Audience :: Developers
Classifier: Intended Audience :: Information Technology
Classifier: Programming Language :: Python
Classifier: Programming Language :: Python :: 3
Classifier: Topic :: System :: Monitoring
Requires-Dist: lifeguard
Requires-Dist: kubernetes
